README.rst
findmodules.py
setup.py
findmodules.egg-info/PKG-INFO
findmodules.egg-info/SOURCES.txt
findmodules.egg-info/dependency_links.txt
findmodules.egg-info/top_level.txt
findmodules.egg-info/zip-safe
test/test.py