Metadata-Version: 1.0
Name: findmodules
Version: 0.6
Summary: Find project module directory relative to the running script.
Home-page: https://github.com/benwbooth/python-findmodules
Author: Ben Booth
Author-email: benwbooth@gmail.com
License: MIT
Keywords: python module import directory path location folder
Platform: UNKNOWN
